connectIO/__init__.py
connectIO/client.py
connectIO/server.py
connectIO/utils.py
connectIO-0.0.3.dist-info/LICENSE
connectIO-0.0.3.dist-info/METADATA
connectIO-0.0.3.dist-info/WHEEL
connectIO-0.0.3.dist-info/top_level.txt
connectIO-0.0.3.dist-info/RECORD
