Metadata-Version: 2.1
Name: connectIO
Version: 0.0.3
Summary: A simple module for sending data across the internet!
Home-page: https://github.com/Den4200/connectIO
Author: Dennis Pham
Author-email: dpham.42@hotmail.com
License: UNKNOWN
Platform: UNKNOWN
Classifier: Programming Language :: Python :: 3
Classifier: License :: OSI Approved :: MIT License
Classifier: Topic :: Communications 
Classifier: Topic :: Communications :: Chat
Classifier: Topic :: Communications :: File Sharing
Classifier: Topic :: Games/Entertainment
Requires-Python: >=3.6
